{"commitInfo":{"timestamp":1728780650581,"operation":"WRITE","operationParameters":{"mode":"Overwrite","partitionBy":"[]"},"isolationLevel":"Serializable","isBlindAppend":false,"operationMetrics":{"numFiles":"1","numOutputRows":"16","numOutputBytes":"1508"},"engineInfo":"Apache-Spark/3.5.3 Delta-Lake/3.2.1","txnId":"bd78cace-1542-4ec3-bba3-87e82b55a972"}}
{"metaData":{"id":"0171dbde-9257-49d5-a700-e6cf178ac272","format":{"provider":"parquet","options":{}},"schemaString":"{\"type\":\"struct\",\"fields\":[{\"name\":\"quarter\",\"type\":\"integer\",\"nullable\":true,\"metadata\":{}},{\"name\":\"year\",\"type\":\"integer\",\"nullable\":true,\"metadata\":{}},{\"name\":\"total_fees\",\"type\":\"long\",\"nullable\":true,\"metadata\":{}},{\"name\":\"total_tickets\",\"type\":\"long\",\"nullable\":true,\"metadata\":{}}]}","partitionColumns":[],"configuration":{},"createdTime":1728780648146}}
{"protocol":{"minReaderVersion":1,"minWriterVersion":2}}
{"add":{"path":"part-00000-e97ecdce-0b17-46ce-bd3f-64db89a6a058-c000.snappy.parquet","partitionValues":{},"size":1508,"modificationTime":1728780650010,"dataChange":true,"stats":"{\"numRecords\":16,\"minValues\":{\"quarter\":1,\"year\":2020,\"total_fees\":13320,\"total_tickets\":279},\"maxValues\":{\"quarter\":4,\"year\":2023,\"total_fees\":99000,\"total_tickets\":2046},\"nullCount\":{\"quarter\":0,\"year\":0,\"total_fees\":0,\"total_tickets\":0}}"}}
